sorna_agent-0.9.14-py3.6-nspkg.pth
sorna/agent/__init__.py
sorna/agent/files.py
sorna/agent/gpu.py
sorna/agent/helper.py
sorna/agent/kernel.py
sorna/agent/resources.py
sorna/agent/server.py
sorna/agent/stats.py
sorna/agent/tests.py
sorna/agent/version.py
sorna_agent-0.9.14.dist-info/DESCRIPTION.rst
sorna_agent-0.9.14.dist-info/METADATA
sorna_agent-0.9.14.dist-info/RECORD
sorna_agent-0.9.14.dist-info/WHEEL
sorna_agent-0.9.14.dist-info/metadata.json
sorna_agent-0.9.14.dist-info/namespace_packages.txt
sorna_agent-0.9.14.dist-info/top_level.txt
