Metadata-Version: 2.0
Name: sorna-agent
Version: 0.9.14
Summary: Sorna agent
Home-page: https://github.com/lablup/sorna-agent
Author: Lablup Inc.
Author-email: joongi@lablup.com
License: LGPLv3
Platform: UNKNOWN
Classifier: Development Status :: 4 - Beta
Classifier: License :: OSI Approved :: GNU Lesser General Public License v3 or later (LGPLv3+)
Classifier: Intended Audience :: Developers
Classifier: Programming Language :: Python
Classifier: Programming Language :: Python :: 3
Classifier: Programming Language :: Python :: 3.6
Classifier: Operating System :: POSIX
Classifier: Operating System :: MacOS :: MacOS X
Classifier: Environment :: No Input/Output (Daemon)
Classifier: Topic :: Scientific/Engineering
Classifier: Topic :: Software Development
Requires-Python: >=3.6
Requires-Dist: ConfigArgParse
Requires-Dist: aiobotocore (>=0.3.0)
Requires-Dist: aiodocker
Requires-Dist: aiohttp (~=2.2.0)
Requires-Dist: aioredis (>=0.2.8)
Requires-Dist: aiozmq (>=0.7)
Requires-Dist: async-timeout (>=1.1)
Requires-Dist: coloredlogs (>=5.2)
Requires-Dist: namedlist
Requires-Dist: pyzmq (>=16.0)
Requires-Dist: requests
Requires-Dist: requests-unixsocket
Requires-Dist: simplejson
Requires-Dist: sorna-common (~=0.9.0)
Requires-Dist: uvloop (>=0.8)
Provides-Extra: build
Requires-Dist: twine; extra == 'build'
Requires-Dist: wheel; extra == 'build'
Provides-Extra: ci
Provides-Extra: dev
Requires-Dist: asynctest; extra == 'dev'
Requires-Dist: flake8; extra == 'dev'
Requires-Dist: pep8-naming; extra == 'dev'
Requires-Dist: pytest (>=3.1); extra == 'dev'
Requires-Dist: pytest-asyncio; extra == 'dev'
Requires-Dist: pytest-mock; extra == 'dev'
Requires-Dist: pytest-sugar; extra == 'dev'
Requires-Dist: twine; extra == 'dev'
Requires-Dist: wheel; extra == 'dev'
Provides-Extra: monitor
Requires-Dist: datadog (>=0.16.0); extra == 'monitor'
Requires-Dist: raven (>=6.1); extra == 'monitor'
Provides-Extra: test
Requires-Dist: asynctest; extra == 'test'
Requires-Dist: flake8; extra == 'test'
Requires-Dist: pep8-naming; extra == 'test'
Requires-Dist: pytest (>=3.1); extra == 'test'
Requires-Dist: pytest-asyncio; extra == 'test'
Requires-Dist: pytest-mock; extra == 'test'
